aws_vibe_guru/__init__.py
aws_vibe_guru/aws_cloudwatch.py
aws_vibe_guru/aws_s3.py
aws_vibe_guru/aws_sqs.py
aws_vibe_guru/cli.py
aws_vibe_guru/cli_helpers.py
aws_vibe_guru-0.1.3.dist-info/METADATA
aws_vibe_guru-0.1.3.dist-info/WHEEL
aws_vibe_guru-0.1.3.dist-info/entry_points.txt
aws_vibe_guru-0.1.3.dist-info/licenses/LICENSE
aws_vibe_guru-0.1.3.dist-info/RECORD
