Metadata-Version: 2.4
Name: aws-vibe-guru
Version: 0.1.3
Summary: A CLI tool for extracting AWS metrics and managing resources (SQS, S3, Lambda Logs)
Project-URL: Homepage, https://github.com/daniellbastos/aws-toolbelt
Project-URL: Documentation, https://github.com/daniellbastos/aws-toolbelt#readme
Project-URL: Repository, https://github.com/daniellbastos/aws-toolbelt
Project-URL: Issues, https://github.com/daniellbastos/aws-toolbelt/issues
Author-email: Daniel Bastos <danielfloresbastos@gmail.com>
License: MIT
License-File: LICENSE
Keywords: aws,cli,cloudwatch,lambda,logs,metrics,monitoring,sqs
Classifier: Development Status :: 3 - Alpha
Classifier: Environment :: Console
Classifier: Intended Audience :: Developers
Classifier: Intended Audience :: System Administrators
Classifier: License :: OSI Approved :: MIT License
Classifier: Operating System :: OS Independent
Classifier: Programming Language :: Python :: 3
Classifier: Programming Language :: Python :: 3.8
Classifier: Programming Language :: Python :: 3.9
Classifier: Programming Language :: Python :: 3.10
Classifier: Programming Language :: Python :: 3.11
Classifier: Programming Language :: Python :: 3.12
Classifier: Topic :: System :: Monitoring
Classifier: Topic :: System :: Systems Administration
Requires-Python: >=3.8.1
Requires-Dist: boto3>=1.26.0
Requires-Dist: rich>=13.0.0
Requires-Dist: typer>=0.9.0
Provides-Extra: dev
Requires-Dist: build>=1.0.0; extra == 'dev'
Requires-Dist: isort>=5.12.0; extra == 'dev'
Requires-Dist: pre-commit>=3.0.0; extra == 'dev'
Requires-Dist: pytest-cov>=4.0.0; extra == 'dev'
Requires-Dist: pytest-mock>=3.10.0; extra == 'dev'
Requires-Dist: pytest>=7.0.0; extra == 'dev'
Requires-Dist: ruff>=0.1.0; extra == 'dev'
Requires-Dist: twine>=4.0.0; extra == 'dev'
